[{"id":1,"name_fi":"Humanistinen ala","name_en":"Humanities","name_sv":"Det humanistiska området","created_at":"2019-05-09T09:59:54.211Z","updated_at":"2019-07-05T10:30:21.039Z"},{"id":2,"name_fi":"Kasvatusala","name_en":"Education","name_sv":"Det pedagogiska området","created_at":"2019-05-07T09:32:52.448Z","updated_at":"2019-07-05T10:30:57.962Z"},{"id":3,"name_fi":"Kauppa ja hallinto","name_en":"Trade and Administration","name_sv":"Ekonomi och förvaltning","created_at":"2019-05-07T09:33:01.518Z","updated_at":"2019-07-05T11:54:01.758Z"},{"id":4,"name_fi":"Luonnontieteet","name_en":"Natural Sciences","name_sv":"De naturvetenskapliga områdena","created_at":"2019-05-07T09:33:12.355Z","updated_at":"2019-07-05T11:54:40.273Z"},{"id":5,"name_fi":"Terveys- ja hyvinvointi","name_en":"Health and Welfare","name_sv":"Hälsovård och välfärd","created_at":"2019-05-07T09:33:22.819Z","updated_at":"2019-07-05T11:55:07.001Z"},{"id":6,"name_fi":"Maa- ja metsätalous","name_en":"Agriculture and Forestry","name_sv":"Lant- och skogsbruk","created_at":"2019-05-07T09:33:33.309Z","updated_at":"2019-07-05T11:55:30.282Z"},{"id":7,"name_fi":"Palvelualat","name_en":"Services","name_sv":"Tjänstebranscher","created_at":"2019-05-07T09:33:45.149Z","updated_at":"2019-07-05T11:55:57.318Z"},{"id":8,"name_fi":"Sosiaaliala","name_en":"Social Services","name_sv":"Sociala området","created_at":"2019-05-07T09:33:56.027Z","updated_at":"2019-07-05T11:56:20.210Z"},{"id":9,"name_fi":"Taiteet ja kulttuuri","name_en":"Arts and Culture","name_sv":"De konstnärliga områdena och kultur","created_at":"2019-05-07T09:34:03.203Z","updated_at":"2019-07-05T11:56:49.544Z"},{"id":10,"name_fi":"Tekniikka","name_en":"Technology","name_sv":"Teknik","created_at":"2019-05-07T09:34:10.767Z","updated_at":"2019-07-05T11:57:15.075Z"},{"id":11,"name_fi":"Tietojenkäsittely ja tieto- ja viestintätekniikka","name_en":"Computing and ICT","name_sv":"Databehandling och informations- och kommunikationsteknik ","created_at":"2019-05-07T09:34:25.498Z","updated_at":"2019-07-05T11:57:43.920Z"},{"id":14,"name_fi":"Yhteiskunnalliset alat","name_en":"Social sciences, journalism and information","name_sv":"Samhällsvetenskapliga området","created_at":"2019-05-17T12:34:15.570Z","updated_at":"2019-07-05T11:58:09.295Z"},{"id":15,"name_fi":"Yleissivistävä koulutus","name_en":"General education","name_sv":"Allmänbildande utbildning","created_at":"2019-05-17T12:35:16.228Z","updated_at":"2019-07-05T11:58:38.832Z"}]